LICENSE
MANIFEST.in
README.md
pyproject.toml
pyquda_pyx.py
setup.py
PyQUDA.egg-info/PKG-INFO
PyQUDA.egg-info/SOURCES.txt
PyQUDA.egg-info/dependency_links.txt
PyQUDA.egg-info/entry_points.txt
PyQUDA.egg-info/requires.txt
PyQUDA.egg-info/top_level.txt
pycparser/LICENSE
pycparser/pycparser/__init__.py
pycparser/pycparser/_ast_gen.py
pycparser/pycparser/_build_tables.py
pycparser/pycparser/_c_ast.cfg
pycparser/pycparser/ast_transforms.py
pycparser/pycparser/c_ast.py
pycparser/pycparser/c_generator.py
pycparser/pycparser/c_lexer.py
pycparser/pycparser/c_parser.py
pycparser/pycparser/plyparser.py
pycparser/pycparser/ply/LICENSE
pycparser/pycparser/ply/__init__.py
pycparser/pycparser/ply/cpp.py
pycparser/pycparser/ply/ctokens.py
pycparser/pycparser/ply/lex.py
pycparser/pycparser/ply/yacc.py
pycparser/pycparser/ply/ygen.py
pycparser/utils/fake_libc_include/_ansi.h
pycparser/utils/fake_libc_include/_fake_defines.h
pycparser/utils/fake_libc_include/_fake_typedefs.h
pycparser/utils/fake_libc_include/_syslist.h
pycparser/utils/fake_libc_include/aio.h
pycparser/utils/fake_libc_include/alloca.h
pycparser/utils/fake_libc_include/ar.h
pycparser/utils/fake_libc_include/argz.h
pycparser/utils/fake_libc_include/assert.h
pycparser/utils/fake_libc_include/complex.h
pycparser/utils/fake_libc_include/cpio.h
pycparser/utils/fake_libc_include/ctype.h
pycparser/utils/fake_libc_include/dirent.h
pycparser/utils/fake_libc_include/dlfcn.h
pycparser/utils/fake_libc_include/emmintrin.h
pycparser/utils/fake_libc_include/endian.h
pycparser/utils/fake_libc_include/envz.h
pycparser/utils/fake_libc_include/errno.h
pycparser/utils/fake_libc_include/fastmath.h
pycparser/utils/fake_libc_include/fcntl.h
pycparser/utils/fake_libc_include/features.h
pycparser/utils/fake_libc_include/fenv.h
pycparser/utils/fake_libc_include/float.h
pycparser/utils/fake_libc_include/fmtmsg.h
pycparser/utils/fake_libc_include/fnmatch.h
pycparser/utils/fake_libc_include/ftw.h
pycparser/utils/fake_libc_include/getopt.h
pycparser/utils/fake_libc_include/glob.h
pycparser/utils/fake_libc_include/grp.h
pycparser/utils/fake_libc_include/iconv.h
pycparser/utils/fake_libc_include/ieeefp.h
