Metadata-Version: 2.1
Name: PyQUDA
Version: 0.10.40
Summary: Python wrapper for QUDA written in Cython
Author-email: SaltyChiang <SaltyChiang@users.noreply.github.com>
Maintainer-email: SaltyChiang <SaltyChiang@users.noreply.github.com>
License: MIT License
Project-URL: Homepage, https://github.com/CLQCD/PyQUDA
Project-URL: Documentation, https://github.com/CLQCD/PyQUDA/wiki/Documentation
Project-URL: Repository, https://github.com/CLQCD/PyQUDA.git
Project-URL: Issues, https://github.com/CLQCD/PyQUDA/issues
Keywords: lattice-gauge-theory,lattice-field-theory,lattice-qcd,hep-lat
Classifier: Development Status :: 2 - Pre-Alpha
Classifier: Programming Language :: Python :: 3 :: Only
Classifier: Programming Language :: Cython
Classifier: Operating System :: POSIX :: Linux
Classifier: Environment :: GPU
Classifier: Environment :: GPU :: NVIDIA CUDA
Classifier: Topic :: Scientific/Engineering :: Physics
Requires-Python: >=3.8
License-File: LICENSE
Requires-Dist: mpi4py
Requires-Dist: numpy
